odoo/addons/partner_iterative_archive/README.rst
odoo/addons/partner_iterative_archive/__init__.py
odoo/addons/partner_iterative_archive/__manifest__.py
odoo/addons/partner_iterative_archive/i18n/partner_iterative_archive.pot
odoo/addons/partner_iterative_archive/models/__init__.py
odoo/addons/partner_iterative_archive/models/res_partner.py
odoo/addons/partner_iterative_archive/readme/CONTRIBUTORS.rst
odoo/addons/partner_iterative_archive/readme/DESCRIPTION.rst
odoo/addons/partner_iterative_archive/static/description/icon.png
odoo/addons/partner_iterative_archive/static/description/index.html
odoo/addons/partner_iterative_archive/tests/__init__.py
odoo/addons/partner_iterative_archive/tests/test_partner_iterative_archive.py
odoo12_addon_partner_iterative_archive-12.0.1.0.0.99.dev2.dist-info/METADATA
odoo12_addon_partner_iterative_archive-12.0.1.0.0.99.dev2.dist-info/WHEEL
odoo12_addon_partner_iterative_archive-12.0.1.0.0.99.dev2.dist-info/top_level.txt
odoo12_addon_partner_iterative_archive-12.0.1.0.0.99.dev2.dist-info/RECORD
